mtba/__init__.py
mtba/logger.py
mtba/sign.py
mtba-0.1.0.dist-info/WHEEL
mtba-0.1.0.dist-info/METADATA
mtba-0.1.0.dist-info/RECORD
